{
  "as_of": "2026-05-15T07:06:52.002174+00:00",
  "total": 20,
  "orders": [
    {
      "id": "052dbaef-3****2be3ed83f0",
      "created_at": "2026-05-15T07:03:24.203200+00:00",
      "pay_way": "WechatPay",
      "price": 1.4,
      "description": "Ace Data Cloud 通用积分充值 - 10 积分"
    },
    {
      "id": "e83dca9c-d****05be4ed79c",
      "created_at": "2026-05-15T07:01:23.124452+00:00",
      "pay_way": "WechatPay",
      "price": 1.4,
      "description": "Ace Data Cloud 通用积分充值 - 10 积分"
    },
    {
      "id": "1c31163b-3****8531a0d730",
      "created_at": "2026-05-15T06:35:02.550051+00:00",
      "pay_way": "AliPay",
      "price": 126.0,
      "description": "Ace Data Cloud 通用积分充值 - 1110 积分"
    },
    {
      "id": "60139beb-8****707301f4cb",
      "created_at": "2026-05-15T06:28:21.234758+00:00",
      "pay_way": "AliPay",
      "price": 126.0,
      "description": "Ace Data Cloud 通用积分充值 - 1110 积分"
    },
    {
      "id": "0fca4c66-4****84dcfd5ce8",
      "created_at": "2026-05-15T06:27:15.629015+00:00",
      "pay_way": "WechatPay",
      "price": 1.4,
      "description": "Ace Data Cloud 通用积分充值 - 10 积分"
    },
    {
      "id": "0c15020c-e****79880920ab",
      "created_at": "2026-05-15T04:01:37.991101+00:00",
      "pay_way": "Stripe",
      "price": 63.2,
      "description": "エースデータクラウド 一般ポイントチャージ - 530 クレジット"
    },
    {
      "id": "a5d529ee-7****48333c5dce",
      "created_at": "2026-05-15T01:47:41.925937+00:00",
      "pay_way": "AliPay",
      "price": 126.0,
      "description": "Ace Data Cloud 通用积分充值 - 1110 积分"
    },
    {
      "id": "59125fda-7****4224c1739b",
      "created_at": "2026-05-15T01:19:07.557589+00:00",
      "pay_way": "WechatPay",
      "price": 126.0,
      "description": "Suno 音乐生成 x 1110 积分"
    },
    {
      "id": "5a396586-d****4d28324184",
      "created_at": "2026-05-14T21:18:36.367472+00:00",
      "pay_way": "X402",
      "price": 1.33,
      "description": "Ace Data Cloud General Points Recharge - 10 Credits"
    },
    {
      "id": "1943cfff-7****81d33f57fd",
      "created_at": "2026-05-14T19:35:49.148255+00:00",
      "pay_way": "X402",
      "price": 12.35,
      "description": "Ace Data Cloud General Points Recharge - 100 Credits"
    },
    {
      "id": "47144cf9-a****3d8279befa",
      "created_at": "2026-05-14T17:53:49.038323+00:00",
      "pay_way": "Stripe",
      "price": 126.0,
      "description": "Suno Music Generation x 1110 Credits"
    },
    {
      "id": "e664d288-4****bd3e874616",
      "created_at": "2026-05-14T17:49:11.521694+00:00",
      "pay_way": "Stripe",
      "price": 126.0,
      "description": "Ace Data Cloud General Points Recharge - 1110 Credits"
    },
    {
      "id": "c8527acf-b****fa53ed61fa",
      "created_at": "2026-05-14T15:45:21.457024+00:00",
      "pay_way": "X402",
      "price": 12.35,
      "description": "Ace Data Cloud General Points Recharge - 100 Credits"
    },
    {
      "id": "b7cd7ddd-8****17952fbc09",
      "created_at": "2026-05-14T15:07:19.868143+00:00",
      "pay_way": "WechatPay",
      "price": 1.4,
      "description": "Ace Data Cloud 通用积分充值 - 10 积分"
    },
    {
      "id": "189d02cb-4****e1301b4228",
      "created_at": "2026-05-14T12:14:27.355089+00:00",
      "pay_way": "WechatPay",
      "price": 1.4,
      "description": "Ace Data Cloud 通用积分充值 - 10 积分"
    },
    {
      "id": "98ffb33b-8****58e0595c3d",
      "created_at": "2026-05-14T11:14:48.970139+00:00",
      "pay_way": "WechatPay",
      "price": 1.4,
      "description": "Ace Data Cloud 通用积分充值 - 10 积分"
    },
    {
      "id": "e4a15dad-7****d57204cb57",
      "created_at": "2026-05-14T09:47:39.350789+00:00",
      "pay_way": "WechatPay",
      "price": 13.0,
      "description": "Nano Banana 图像生成 x 100 积分"
    },
    {
      "id": "f589d9b2-c****371e73cc64",
      "created_at": "2026-05-14T08:05:12.666378+00:00",
      "pay_way": "WechatPay",
      "price": 1.4,
      "description": "Ace Data Cloud 通用积分充值 - 10 积分"
    },
    {
      "id": "05e34285-2****36c9c8684f",
      "created_at": "2026-05-14T07:52:33.871197+00:00",
      "pay_way": "WechatPay",
      "price": 1.4,
      "description": "Ace Data Cloud 通用积分充值 - 10 积分"
    },
    {
      "id": "51b2d53a-6****6126324b73",
      "created_at": "2026-05-14T07:44:22.318843+00:00",
      "pay_way": "WechatPay",
      "price": 13.0,
      "description": "Ace Data Cloud 通用积分充值 - 100 积分"
    }
  ]
}
