{
  "as_of": "2026-07-11T06:46:18.085260+00:00",
  "total": 20,
  "orders": [
    {
      "id": "c8ebe0ca-d****c2d98b0cbc",
      "created_at": "2026-07-11T06:30:13.576412+00:00",
      "pay_way": "AliPay",
      "price": 15.0,
      "description": "Ace Data Cloud 通用积分充值 - 100 积分"
    },
    {
      "id": "9804d820-4****fafb5ef2bd",
      "created_at": "2026-07-11T05:25:13.429358+00:00",
      "pay_way": "WechatPay",
      "price": 15.0,
      "description": "Ace Data Cloud 通用积分充值 - 100 积分"
    },
    {
      "id": "30ff0f40-e****5459123b92",
      "created_at": "2026-07-11T04:46:48.771237+00:00",
      "pay_way": "WechatPay",
      "price": 126.0,
      "description": "Ace Data Cloud 通用积分充值 - 1110 积分"
    },
    {
      "id": "9370b38b-2****a768504aa8",
      "created_at": "2026-07-10T22:37:27.768550+00:00",
      "pay_way": "Stripe",
      "price": 15.0,
      "description": "Ace Data Cloud General Points Recharge - 100 Credits"
    },
    {
      "id": "f5772bea-3****c7ecee032f",
      "created_at": "2026-07-10T22:18:06.916307+00:00",
      "pay_way": "Stripe",
      "price": 66.5,
      "description": "Ace Data Cloud General Points Recharge - 530 Credits"
    },
    {
      "id": "b8766ac6-b****cb54668305",
      "created_at": "2026-07-10T20:42:50.520902+00:00",
      "pay_way": "Stripe",
      "price": 647.0,
      "description": "Suno Music Generation x 5950 Credits"
    },
    {
      "id": "12a79cdd-6****5addf67d1a",
      "created_at": "2026-07-10T18:04:28.711602+00:00",
      "pay_way": "Stripe",
      "price": 15.0,
      "description": "Нано Банан генерация изображений x 100 Кредиты"
    },
    {
      "id": "275e5407-f****fa8f0e9065",
      "created_at": "2026-07-10T17:59:00.813600+00:00",
      "pay_way": "Stripe",
      "price": 647.0,
      "description": "Пополнение универсальных баллов Ace Data Cloud - 5950 Кредиты"
    },
    {
      "id": "5168b428-1****be97e489f2",
      "created_at": "2026-07-10T15:44:47.561401+00:00",
      "pay_way": "WechatPay",
      "price": 15.0,
      "description": "Ace Data Cloud 通用积分充值 - 100 积分"
    },
    {
      "id": "cebe064d-c****ca752f3c4a",
      "created_at": "2026-07-10T13:21:52.666336+00:00",
      "pay_way": "WechatPay",
      "price": 15.0,
      "description": "Ace Data Cloud 通用积分充值 - 100 积分"
    },
    {
      "id": "b072bd6e-9****5208b56077",
      "created_at": "2026-07-10T13:00:11.187508+00:00",
      "pay_way": "Stripe",
      "price": 15.0,
      "description": "Ace Data Cloud Credits x 100.0"
    },
    {
      "id": "fc1cdb56-d****7f2f0e8705",
      "created_at": "2026-07-10T12:51:47.628315+00:00",
      "pay_way": "Stripe",
      "price": 1313.0,
      "description": "Ace Data Cloud General Points Recharge - 12500 Credits"
    },
    {
      "id": "d14ff2d5-6****df36dc7521",
      "created_at": "2026-07-10T12:06:58.073547+00:00",
      "pay_way": "AliPay",
      "price": 126.0,
      "description": "Suno 音乐生成 x 1110 积分"
    },
    {
      "id": "e75a4ebe-4****dcbbbad1db",
      "created_at": "2026-07-10T11:09:37.340766+00:00",
      "pay_way": "WechatPay",
      "price": 15.0,
      "description": "Ace Data Cloud 通用积分充值 - 100 积分"
    },
    {
      "id": "c4a15ab5-8****e35b77a3f6",
      "created_at": "2026-07-10T09:55:51.393973+00:00",
      "pay_way": "Stripe",
      "price": 1313.0,
      "description": "Suno Music Generation x 12500 Credits"
    },
    {
      "id": "e826652b-a****c467591fa1",
      "created_at": "2026-07-10T09:21:14.165722+00:00",
      "pay_way": "WechatPay",
      "price": 15.0,
      "description": "Ace Data Cloud 通用积分充值 - 100 积分"
    },
    {
      "id": "2f4b17bc-8****1f1820e44f",
      "created_at": "2026-07-10T08:23:33.577753+00:00",
      "pay_way": "WechatPay",
      "price": 15.0,
      "description": "Ace Data Cloud 通用积分充值 - 100 积分"
    },
    {
      "id": "44e0de56-6****ddde765c2c",
      "created_at": "2026-07-10T07:07:49.248218+00:00",
      "pay_way": "WechatPay",
      "price": 15.0,
      "description": "Ace Data Cloud 通用积分充值 - 100 积分"
    },
    {
      "id": "9c6ac197-e****b7622f657d",
      "created_at": "2026-07-10T03:26:00.303905+00:00",
      "pay_way": "WechatPay",
      "price": 66.5,
      "description": "Ace Data Cloud 通用积分充值 - 530 积分"
    },
    {
      "id": "9dc3698e-f****3b2fa368eb",
      "created_at": "2026-07-10T03:17:00.698121+00:00",
      "pay_way": "Stripe",
      "price": 15.0,
      "description": "에이스 데이터 클라우드 일반 포인트 충전 - 100 포인트"
    }
  ]
}
